[
    {
        "Origin_Event": "going out on thursdays is a terrible idea. i knew there was a reason i haven`t done it all quarter. *pops advil*",
        "Event": "Going out on Thursdays is a terrible idea."
    },
    {
        "Origin_Event": " No FAIR!",
        "Event": "It's not fair."
    },
    {
        "Origin_Event": "Getting bored sitting at the hotel room the entire day",
        "Event": "Getting bored sitting at the hotel room the entire day"
    },
    {
        "Origin_Event": "#bgt It`s a shame that the Dreambears won`t get through",
        "Event": "The Dreambears won't get through"
    },
    {
        "Origin_Event": "i dont like funerals",
        "Event": "I attended a funeral."
    },
    {
        "Origin_Event": "The Taxi Q at Pelangi was super loooong.. and now I`m getting headaches because of the hot-cold transition",
        "Event": "I got headaches because of the hot-cold transition."
    },
    {
        "Origin_Event": "head hurt",
        "Event": "Head hurt"
    },
    {
        "Origin_Event": "have been to portugal. and spain. and has a sore throat. scary?",
        "Event": "Has a sore throat."
    },
    {
        "Origin_Event": "Have been feeling very sick    had day off today... ARRRGH",
        "Event": "I have been feeling very sick"
    },
    {
        "Origin_Event": " i didnt get the msg!! :`( but i bought princess",
        "Event": "I didn't get the message."
    },
    {
        "Origin_Event": "Got back from Arizona yesterday.  Moved the furniture and stuff out of the Arizona house and shipped it to Redwood City.    How sad.",
        "Event": "Had to move out of the Arizona house."
    },
    {
        "Origin_Event": "  Ah bad times   I hate exams. I feel so unprepared this time as well. Sucks haha.",
        "Event": "I felt unprepared for an exam."
    },
    {
        "Origin_Event": "Jane is really sad because she probably won`t get perfect on tonight`s quiz without the missing article. Should`ve asked someone for it.",
        "Event": "I didn't get a perfect score on the quiz."
    },
    {
        "Origin_Event": "Hadnt cried in such a long time",
        "Event": "I cried"
    },
    {
        "Origin_Event": "A year from now is graduation....i am pretty sure i`m not ready for it!?!?!?",
        "Event": "I'm not ready for graduation."
    },
    {
        "Origin_Event": "has such a freakin migraine",
        "Event": "I had a freakin' migraine"
    },
    {
        "Origin_Event": " haha okay you were talking about middle college grad I think and I got worried",
        "Event": "I got worried"
    },
    {
        "Origin_Event": "There`s a spider in my room. Save me...",
        "Event": "There's a spider in my room."
    },
    {
        "Origin_Event": " don`t i know it! i live in the middle of nowhere, my house is spider central",
        "Event": "I live in a house infested with spiders."
    },
    {
        "Origin_Event": "finally graduation no more school ... im sick today",
        "Event": "I'm sick today"
    },
    {
        "Origin_Event": " Neither could i! And i looked on ebay and it was like 250 euro for two!!!! but i doubt my parents would fork that amount out",
        "Event": "My parents wouldn't fork out a large amount of money."
    },
    {
        "Origin_Event": " unfortunately I am stuck at work so I can`t get said prize",
        "Event": "Stuck at work"
    },
    {
        "Origin_Event": "'AAARRRGGGGHHH' is the only thing that can decribe how I feel rite now!",
        "Event": "I feel extremely frustrated or angry."
    },
    {
        "Origin_Event": "Sitting at the Connection listening to the employees reminisce and mope about their last shift",
        "Event": "reminiscing about last shift"
    },
    {
        "Origin_Event": " Nicky, I LAND at 10pm, it will be like 10:40 before I get home! UGH! Wont be any fish fry left for me anyways",
        "Event": "I won't have any fish fry left for me."
    },
    {
        "Origin_Event": "this sucks schools over and there is nothing to do",
        "Event": "There is nothing to do at school."
    },
    {
        "Origin_Event": "I`m so hungry",
        "Event": "I'm so hungry"
    },
    {
        "Origin_Event": "Off to bed I go to dream of a world where Wal-Mart and Liquor stores all get blown up",
        "Event": "Wal-Mart and Liquor stores get blown up"
    },
    {
        "Origin_Event": " ohhh ok. thats upsetting  sorry for wasting your time. ****",
        "Event": "Wasting someone's time."
    },
    {
        "Origin_Event": "So bummed that I can`t see LTJ in June  hoping for a UK yoke soon",
        "Event": "Can't see LTJ in June."
    },
    {
        "Origin_Event": " It`s a lie just like the restaraunt named 'Garfields'... he is nowhere to be found",
        "Event": "I was deceived by a false claim."
    },
    {
        "Origin_Event": "My eyes hurt",
        "Event": "My eyes hurt"
    },
    {
        "Origin_Event": "My TI89 died. I don`t know why.",
        "Event": "My TI89 died."
    },
    {
        "Origin_Event": "unemployment line here i come.",
        "Event": "I became unemployed."
    },
    {
        "Origin_Event": "bad mood now",
        "Event": "Having a bad mood"
    },
    {
        "Origin_Event": "The CD  player in my car is broken.  So much for listening to my Kidz Bop Happy Meal CD.",
        "Event": "My car's CD player is broken."
    },
    {
        "Origin_Event": " oh @ work? poor boy",
        "Event": "Having a bad day at work"
    },
    {
        "Origin_Event": "  I am not a ****! damnit!  [sending you an e-mail right now btw]",
        "Event": "Being called a derogatory term."
    },
    {
        "Origin_Event": "Getting a cleaning on tues then getting a tooth pulled on thurs. Then gotta schedule a bridge that might need a root canal--ugh.",
        "Event": "Getting a tooth pulled, scheduling a bridge that might need a root canal."
    },
    {
        "Origin_Event": "hm seems to have been because my blog was marked as a phishing site",
        "Event": "My blog was marked as a phishing site"
    },
    {
        "Origin_Event": " - they have their headaches the morning after, instead!",
        "Event": "They had a headache the morning after"
    }
]